README.md
setup.py
kdxfsdk/__init__.py
kdxfsdk/ali_audio.py
kdxfsdk/ali_camera.py
kdxfsdk/ali_driver.py
kdxfsdk/ali_iat.py
kdxfsdk/ali_image.py
kdxfsdk/ali_motor.py
kdxfsdk/ali_qa.py
kdxfsdk/ali_record.py
kdxfsdk/ali_tts.py
kdxfsdk/config_defaults.py
kdxfsdk.egg-info/PKG-INFO
kdxfsdk.egg-info/SOURCES.txt
kdxfsdk.egg-info/dependency_links.txt
kdxfsdk.egg-info/requires.txt
kdxfsdk.egg-info/top_level.txt
kdxfsdk/robot/Player.py
kdxfsdk/robot/__init__.py
kdxfsdk/robot/config.py
kdxfsdk/robot/constants.py
kdxfsdk/robot/logging.py
kdxfsdk/robot/utils.py
kdxfsdk/snowboy/__init__.py
kdxfsdk/snowboy/snowboydecoder.py
kdxfsdk/snowboy/snowboydetect.py