Metadata-Version: 1.0
Name: kdxfsdk
Version: 0.0.33
Summary: kdxf sdk
Home-page: http://xialingming
Author: lmxia
Author-email: xialingming@gmail.com
License: MIT Licence
Keywords: kdxf,sdk,xialingming
Platform: any
